nonrad-1.2.0.dist-info/METADATA
nonrad-1.2.0.dist-info/WHEEL
nonrad-1.2.0.dist-info/licenses/LICENSE
nonrad/__init__.py
nonrad/__pycache__/nonrad.analytic_overlap_NM-126.py311.1.nbc
nonrad/__pycache__/nonrad.analytic_overlap_NM-126.py311.nbi
nonrad/__pycache__/nonrad.analytic_overlap_NM-127.py311.1.nbc
nonrad/__pycache__/nonrad.analytic_overlap_NM-127.py311.nbi
nonrad/__pycache__/nonrad.analytic_overlap_NM-127.py39.1.nbc
nonrad/__pycache__/nonrad.analytic_overlap_NM-127.py39.nbi
nonrad/__pycache__/nonrad.analytic_overlap_NM-128.py310.1.nbc
nonrad/__pycache__/nonrad.analytic_overlap_NM-128.py310.nbi
nonrad/__pycache__/nonrad.analytic_overlap_NM-128.py38.1.nbc
nonrad/__pycache__/nonrad.analytic_overlap_NM-128.py38.nbi
nonrad/__pycache__/nonrad.analytic_overlap_NM-128.py39.1.nbc
nonrad/__pycache__/nonrad.analytic_overlap_NM-128.py39.2.nbc
nonrad/__pycache__/nonrad.analytic_overlap_NM-128.py39.nbi
nonrad/__pycache__/nonrad.analytic_overlap_NM-172.py311.1.nbc
nonrad/__pycache__/nonrad.analytic_overlap_NM-172.py311.nbi
nonrad/__pycache__/nonrad.analytic_overlap_NM-173.py311.1.nbc
nonrad/__pycache__/nonrad.analytic_overlap_NM-173.py311.nbi
nonrad/__pycache__/nonrad.analytic_overlap_NM-173.py38.1.nbc
nonrad/__pycache__/nonrad.analytic_overlap_NM-173.py38.nbi
nonrad/__pycache__/nonrad.analytic_overlap_NM-174.py310.1.nbc
nonrad/__pycache__/nonrad.analytic_overlap_NM-174.py310.nbi
nonrad/__pycache__/nonrad.analytic_overlap_NM-174.py39.1.nbc
nonrad/__pycache__/nonrad.analytic_overlap_NM-174.py39.nbi
nonrad/__pycache__/nonrad.analytic_overlap_NM-184.py310.1.nbc
nonrad/__pycache__/nonrad.analytic_overlap_NM-184.py310.nbi
nonrad/__pycache__/nonrad.analytic_overlap_NM-187.py310.1.nbc
nonrad/__pycache__/nonrad.analytic_overlap_NM-187.py310.2.nbc
nonrad/__pycache__/nonrad.analytic_overlap_NM-187.py310.nbi
nonrad/__pycache__/nonrad.fact-59.py311.1.nbc
nonrad/__pycache__/nonrad.fact-59.py311.nbi
nonrad/__pycache__/nonrad.fact-60.py311.1.nbc
nonrad/__pycache__/nonrad.fact-60.py311.nbi
nonrad/__pycache__/nonrad.fact-60.py39.1.nbc
nonrad/__pycache__/nonrad.fact-60.py39.nbi
nonrad-1.2.0.dist-info/RECORD
