Metadata-Version: 2.1
Name: nonrad
Version: 1.2.0
Summary: Implementation for computing nonradiative recombination rates in semiconductors
Keywords: physics materials science VASP recombination Shockley-Read-Hall
Author-Email: Mark E. Turiansky <mturiansky@ucsb.edu>
License: MIT
Classifier: Programming Language :: Python :: 3
Classifier: Programming Language :: Python :: 3.9
Classifier: Programming Language :: Python :: 3.10
Classifier: Programming Language :: Python :: 3.11
Classifier: License :: OSI Approved :: MIT License
Classifier: Operating System :: OS Independent
Project-URL: Documentation, https://nonrad.readthedocs.io
Project-URL: Repository, https://github.com/mturiansky/nonrad
Requires-Python: >=3.9
Requires-Dist: numpy>=1.24.3
Requires-Dist: scipy>=1.9.3
Requires-Dist: pymatgen>=2023.3.23
Requires-Dist: monty>=2023.4.10
Requires-Dist: numba>=0.57.0
Requires-Dist: mpmath>=1.3.0
